{
  "responseCoverage": {
    "200": [
      {
        "testSteps": [
          {
            "executionResult": {
              "requestHeaders": {
                "Accept": [
                  "application/json"
                ],
                "User-Agent": [
                  "Mozilla/5.0 (Macintosh; Intel Mac OS X x.y; rv:42.0) Gecko/20100101 Firefox/42.0"
                ]
              },
              "requestUrl": "https://ntp1node.nebl.io//ntp1/tokenid/22",
              "responseBody": "{\"type\":\"Buffer\",\"data\":[]}",
              "responseHeaders": {
                "Server": [
                  "nginx/1.10.3 (Ubuntu)"
                ],
                "Date": [
                  "Mon, 07 Oct 2019 23:42:59 GMT"
                ],
                "Content-Type": [
                  "application/json; charset\u003dutf-8"
                ],
                "Content-Length": [
                  "27"
                ],
                "Connection": [
                  "keep-alive"
                ],
                "X-Powered-By": [
                  "Express"
                ],
                "Access-Control-Allow-Headers": [
                  "Content-Type, api_key"
                ],
                "ETag": [
                  "W/\"1b-9007838\""
                ],
                "Last-Modified": [
                  "Monday, 07-Oct-2019 23:42:59 GMT"
                ],
                "Cache-Control": [
                  "no-store, no-cache, must-revalidate, proxy-revalidate, max-age\u003d0"
                ],
                "OkHttp-Sent-Millis": [
                  "1570491768986"
                ],
                "OkHttp-Received-Millis": [
                  "1570491769178"
                ]
              },
              "statusCode": 200
            },
            "httpMethod": "GET",
            "operationId": "getTokenId",
            "originalParameter": {
              "parameterName": "tokensymbol",
              "sanitizedName": "tokensymbol",
              "value": "dRbPMvfYhLWNBBEgSAX"
            },
            "parameters": [
              {
                "parameterName": "tokensymbol",
                "sanitizedName": "tokensymbol",
                "value": "22"
              }
            ],
            "statusCode": 200,
            "violatedConstraint": "Wrong data type"
          }
        ],
        "authentication": {
          "authenticated": false
        }
      }
    ]
  },
  "target": {
    "httpMethod": "GET",
    "operationId": "getTokenId"
  }
}